MANIFEST.in
README.md
run_misa.py
setup.py
data/backbone.nwk
data/dist.mat
data/meta_backbone.tree
data/out.jplace
data/out.tog.tre
data/out.tree
data/out_jac.tree
misa/Core.py
misa/Distance.py
misa/Method.py
misa/Model.py
misa/Optimize.py
misa/__init__.py
misa/jutil.py
misa/util.py
misa.egg-info/PKG-INFO
misa.egg-info/SOURCES.txt
misa.egg-info/dependency_links.txt
misa.egg-info/not-zip-safe
misa.egg-info/requires.txt
misa.egg-info/top_level.txt