Metadata-Version: 2.1
Name: misa
Version: 1.0.0
Summary: MISA: a mixed samples analysis tool
Home-page: https://github.com/balabanmetin/misa
Author: Metin Balaban
Author-email: balaban@ucsd.edu
License: UNKNOWN
Platform: UNKNOWN
